faim_client/__init__.py
faim_client/api/__init__.py
faim_client/api/forecast/__init__.py
faim_client/api/forecast/forecast_v1_ts_forecast_model_name_model_version_post.py
faim_client/api/health/__init__.py
faim_client/api/health/health_check_health_get.py
faim_client/api/tabular/__init__.py
faim_client/api/tabular/predict_tabular_v1_tabular_predict_model_name_model_version_post.py
faim_client/client.py
faim_client/errors.py
faim_client/models/__init__.py
faim_client/models/api_key_validation_response.py
faim_client/models/api_usage_stats_response.py
faim_client/models/checkout_session_status_response.py
faim_client/models/create_checkout_session_request.py
faim_client/models/create_checkout_session_response.py
faim_client/models/dataset_info_response.py
faim_client/models/dataset_list_item_response.py
faim_client/models/dataset_list_response.py
faim_client/models/dataset_type.py
faim_client/models/error_code.py
faim_client/models/error_response.py
faim_client/models/http_validation_error.py
faim_client/models/model_name.py
faim_client/models/start_upload_metadata.py
faim_client/models/start_upload_request.py
faim_client/models/start_upload_response.py
faim_client/models/tabular_start_upload_metadata.py
faim_client/models/validation_error.py
faim_client/types.py
faim_sdk/__init__.py
faim_sdk/client.py
faim_sdk/eval/__init__.py
faim_sdk/eval/metrics.py
faim_sdk/eval/py.typed
faim_sdk/eval/visualization.py
faim_sdk/exceptions.py
faim_sdk/models.py
faim_sdk/py.typed
faim_sdk/tabular_client.py
faim_sdk/utils.py
faim_sdk-0.5.1.dist-info/METADATA
faim_sdk-0.5.1.dist-info/WHEEL
faim_sdk-0.5.1.dist-info/RECORD
