Metadata-Version: 2.3
Name: faim-sdk
Version: 0.5.1
Summary: Python SDK for FAIM time-series forecasting with foundation AI models
License: Apache-2.0
Author: FAIM
Author-email: info@faim.it.com
Requires-Python: >=3.10,<4.0
Classifier: License :: OSI Approved :: Apache Software License
Classifier: Programming Language :: Python :: 3
Classifier: Programming Language :: Python :: 3.10
Classifier: Programming Language :: Python :: 3.11
Classifier: Programming Language :: Python :: 3.12
Classifier: Programming Language :: Python :: 3.13
Requires-Dist: attrs (>=22.2.0)
Requires-Dist: httpx (>=0.23.0,<0.29.0)
Requires-Dist: matplotlib (>=3.5.0)
Requires-Dist: numpy (>=1.26.0,<2.0.0)
Requires-Dist: pyarrow (>=18.1.0)
